LattesLab/__init__.py
LattesLab-0.10.3.dist-info/LICENSE.txt
LattesLab-0.10.3.dist-info/METADATA
LattesLab-0.10.3.dist-info/WHEEL
LattesLab-0.10.3.dist-info/top_level.txt
LattesLab-0.10.3.dist-info/RECORD
