Metadata-Version: 2.1
Name: LattesLab
Version: 0.10.3
Summary: Set of tools to generate data products originated by Lattes CV files.
Home-page: https://github.com/tcodingprojects/LattesLab
Author: Thiago Santana
Author-email: thiagoluis@gmail.com
License: MIT
Platform: UNKNOWN
Requires-Dist: wordcloud
Requires-Dist: scipy
Requires-Dist: datetime
Requires-Dist: matplotlib
Requires-Dist: sklearn
Requires-Dist: networkx
Requires-Dist: numpy
Requires-Dist: pandas
Requires-Dist: scikit-fuzzy
